{
  "type": "Feature",
  "geometry": {
    "type": "Point",
    "coordinates": [
      2.319994,
      48.869196
    ]
  },
  "properties": {
    "extraction": {
      "toponyme": "Hôtel de Guébriant, aujourd'hui Rothschild",
      "adresse": "33 rue du Faubourg Saint-Honoré",
      "voie": "rue du Faubourg Saint-Honoré",
      "ville": "Paris",
      "pays": "France"
    },
    "query": "33 rue du Faubourg Saint-Honoré, Paris, France",
    "level": "adresse",
    "response": {
      "place_id": 89191962,
      "licence": "Data © OpenStreetMap contributors, ODbL 1.0. http://osm.org/copyright",
      "osm_type": "node",
      "osm_id": 842127582,
      "lat": "48.8691964",
      "lon": "2.3199937",
      "class": "place",
      "type": "house",
      "place_rank": 30,
      "importance": 9.317235065227768e-05,
      "addresstype": "place",
      "name": "",
      "display_name": "33, Rue du Faubourg Saint-Honoré, Quartier de la Madeleine, Paris 8e Arrondissement, Paris, Île-de-France, France métropolitaine, 75008, France",
      "boundingbox": [
        "48.8691464",
        "48.8692464",
        "2.3199437",
        "2.3200437"
      ]
    },
    "photo_id": "cb40266942x"
  }
}